zk_dtypes/__init__.py
zk_dtypes/_iinfo.py
zk_dtypes/_pfinfo.py
zk_dtypes/_zk_dtypes_ext.cpython-312-darwin.so
zk_dtypes/py.typed
zk_dtypes-0.0.3.dist-info/licenses/LICENSE
zk_dtypes-0.0.3.dist-info/licenses/LICENSE.chromium
zk_dtypes-0.0.3.dist-info/licenses/LICENSE.eigen
zk_dtypes-0.0.3.dist-info/METADATA
zk_dtypes-0.0.3.dist-info/WHEEL
zk_dtypes-0.0.3.dist-info/top_level.txt
zk_dtypes-0.0.3.dist-info/RECORD
