Metadata-Version: 2.4
Name: zk_dtypes
Version: 0.0.3
Summary: zk_dtypes is a stand-alone implementation of several NumPy dtype extensions used in Zero Knowledge.
Author-email: zk_dtypes authors <contact@fractalyze.io>
License-Expression: Apache-2.0
Project-URL: homepage, https://github.com/fractalyze/zk_dtypes
Project-URL: repository, https://github.com/fractalyze/zk_dtypes
Classifier: Programming Language :: Python :: 3
Classifier: Programming Language :: Python :: 3 :: Only
Classifier: Intended Audience :: Science/Research
Requires-Python: >=3.11
License-File: LICENSE
License-File: LICENSE.chromium
License-File: LICENSE.eigen
Requires-Dist: numpy>=2.3.5
Provides-Extra: dev
Requires-Dist: absl-py; extra == "dev"
Requires-Dist: pytest; extra == "dev"
Requires-Dist: pytest-xdist; extra == "dev"
Requires-Dist: pylint; extra == "dev"
Requires-Dist: pyink; extra == "dev"
Dynamic: license-file
